src/__init__.py
src/__main__.py
src/server.py
quickchat_ai_mcp-0.0.11.dist-info/METADATA
quickchat_ai_mcp-0.0.11.dist-info/WHEEL
quickchat_ai_mcp-0.0.11.dist-info/entry_points.txt
quickchat_ai_mcp-0.0.11.dist-info/licenses/LICENSE
quickchat_ai_mcp-0.0.11.dist-info/RECORD
