Metadata-Version: 2.4
Name: quickchat-ai-mcp
Version: 0.0.11
Summary: Quickchat AI MCP Server
Author-email: Piotr Grudzien <piotr@quickchat.ai>, Mateusz Jakubczak <mateusz@quickchat.ai>
License-File: LICENSE
Keywords: ai-agent,mcp,quickchat
Requires-Python: >=3.11
Requires-Dist: mcp>=1.0.0
Requires-Dist: mcp[cli]>=1.6.0
Requires-Dist: python-dotenv>=1.1.0
Requires-Dist: requests>=2.31.0
Provides-Extra: test
Requires-Dist: pytest; extra == 'test'
Requires-Dist: pytest-asyncio; extra == 'test'
